viewstate/__init__.py
viewstate/__main__.py
viewstate/colors.py
viewstate/exceptions.py
viewstate/parse.py
viewstate/viewstate.py
viewstate-0.7.0.dist-info/licenses/LICENSE
viewstate-0.7.0.dist-info/METADATA
viewstate-0.7.0.dist-info/WHEEL
viewstate-0.7.0.dist-info/top_level.txt
viewstate-0.7.0.dist-info/RECORD
