Metadata-Version: 2.4
Name: viewstate
Version: 0.7.0
Summary: ASP.NET View State Decoder
Author-email: Yuval Adam <_@yuv.al>
License-Expression: MIT
Requires-Python: >=3.8
License-File: LICENSE
Dynamic: license-file
